arachno/__init__.py
arachno/duration.py
arachno/exc.py
arachno/executor.py
arachno/expr.py
arachno/internal.py
arachno/planner.py
arachno/request.py
arachno/response.py
arachno-0.3.0.dist-info/LICENSE
arachno-0.3.0.dist-info/METADATA
arachno-0.3.0.dist-info/WHEEL
arachno-0.3.0.dist-info/top_level.txt
arachno-0.3.0.dist-info/RECORD
