Metadata-Version: 2.1
Name: arachno
Version: 0.3.0
Summary: DSL for coroutine orchestration
Home-page: https://github.com/palestamp/arachno
Author: Stas Kazhavets
Author-email: stas.kozhevets@gmail.com
License: UNKNOWN
Platform: UNKNOWN
Classifier: Programming Language :: Python :: 3
Requires-Dist: jmespath
Requires-Dist: toposort
Requires-Dist: attr
Requires-Dist: cached-property
Requires-Dist: typing-extensions
